simple_package/__init__.py
simple_package/string_utils.py
simple_package_yeonjin-0.1.0.dist-info/METADATA
simple_package_yeonjin-0.1.0.dist-info/WHEEL
simple_package_yeonjin-0.1.0.dist-info/top_level.txt
simple_package_yeonjin-0.1.0.dist-info/RECORD
