Metadata-Version: 2.1
Name: simple-package-yeonjin
Version: 0.1.0
Summary: A simple package for reversing strings
Home-page: https://github.com/kangyeonjin/simple_package.git
Author: yeonjin
Author-email: yeonjin917n.n@gmail.com
Classifier: Programming Language :: Python :: 3
Classifier: License :: OSI Approved :: MIT License
Classifier: Operating System :: OS Independent
Requires-Python: >=3.6
